nsimport/__init__.py
nsimport/_bootstrap.py
nsimport/_bootstrap_external.py
nsimport/abc.py
nsimport/machinery.py
nsimport/metadata.py
nsimport/nsimporter_internal.py
nsimport/resources.py
nsimport/util.py
nsimport-0.1.3.dist-info/LICENSE
nsimport-0.1.3.dist-info/METADATA
nsimport-0.1.3.dist-info/WHEEL
nsimport-0.1.3.dist-info/top_level.txt
nsimport-0.1.3.dist-info/RECORD
