Metadata-Version: 2.1
Name: nsimport
Version: 0.1.3
Summary: Import modules to independent namespaces (not load to sys.modules) with modified difflib.
Home-page: https://github.com/universetraveller/nsimport_python
Author: universetraveller
Author-email: universetraveller@outlook.com
License: MIT
Platform: UNKNOWN
Classifier: License :: OSI Approved :: MIT License
Classifier: Programming Language :: Python
Classifier: Programming Language :: Python :: 3
Classifier: Programming Language :: Python :: 3.8
Classifier: Programming Language :: Python :: Implementation :: CPython
Requires-Python: >=3.8.0
License-File: LICENSE
